dashify/__init__.py
dashify/aggregation/__init__.py
dashify/aggregation/aggregator.py
dashify/logging/__init__.py
dashify/logging/dashify_logging.py
dashify/metrics/__init__.py
dashify/metrics/processor.py
dashify/visualization/__init__.py
dashify/visualization/app.py
dashify/visualization/layout_definition.py
dashify/visualization/run_server.py
dashify/visualization/assets/css/base_styles.css
dashify/visualization/assets/css/custom_styles.css
dashify/visualization/assets/img/dashify_logo.png
dashify/visualization/assets/img/dashify_logo.svg
dashify/visualization/assets/img/dashify_logo_2.png
dashify/visualization/assets/img/dashify_logo_2_scaled.png
dashify/visualization/controllers/__init__.py
dashify/visualization/controllers/cache_controller.py
dashify/visualization/controllers/cell_data_types.py
dashify/visualization/controllers/data_controllers.py
dashify/visualization/data_export/__init__.py
dashify/visualization/data_export/analysis_file.py
dashify/visualization/data_import/__init__.py
dashify/visualization/data_import/data_loaders.py
dashify/visualization/data_model/__init__.py
dashify/visualization/data_model/experiment.py
dashify/visualization/data_model/grid_search_result.py
dashify/visualization/plotting/__init__.py
dashify/visualization/plotting/utils.py
dashify/visualization/tabs/__init__.py
dashify/visualization/tabs/tab_experiments_table.py
dashify/visualization/tabs/tab_graph_grids.py
dashify/visualization/tabs/tab_settings.py
dashifyML-0.1.3.data/scripts/dashify-vis
dashifyML-0.1.3.dist-info/METADATA
dashifyML-0.1.3.dist-info/WHEEL
dashifyML-0.1.3.dist-info/top_level.txt
dashifyML-0.1.3.dist-info/RECORD
